radius_clustering/__init__.py
radius_clustering/algorithms.py
radius_clustering/radius_clustering.py
radius_clustering/utils/__init__.py
radius_clustering/utils/_emos.cp311-win_amd64.pyd
radius_clustering/utils/_mds_approx.cp311-win_amd64.pyd
radius_clustering/utils/emos.c
radius_clustering/utils/emos.pyx
radius_clustering/utils/main-emos.c
radius_clustering/utils/mds.cpp
radius_clustering/utils/mds.pyx
radius_clustering/utils/mds3-util.h
radius_clustering/utils/mds_core.cpp
radius_clustering/utils/random_manager.cpp
radius_clustering/utils/random_manager.h
radius_clustering/utils/util_heap.h
radius_clustering-1.4.2.dist-info/licenses/LICENSE
radius_clustering-1.4.2.dist-info/METADATA
radius_clustering-1.4.2.dist-info/WHEEL
radius_clustering-1.4.2.dist-info/top_level.txt
radius_clustering-1.4.2.dist-info/RECORD
