Metadata-Version: 2.4
Name: radius-clustering
Version: 1.4.2
Summary: A Clustering under radius constraints algorithm using minimum dominating sets
Author: Quentin Haenn, Lias Laboratory
Maintainer-email: Quentin Haenn <quentin.haenn.pro@gmail.com>
License:                     GNU GENERAL PUBLIC LICENSE
Project-URL: source, https://github.com/scikit-learn-contrib/radius_clustering
Project-URL: tracker, https://github.com/scikit-learn-contrib/radius_clustering/issues
Project-URL: documentation, https://contrib.scikit-learn.org/radius_clustering/
Keywords: Unsupervised learning,clustering,minimum dominating sets,clustering under radius constraint
Classifier: Development Status :: 5 - Production/Stable
Classifier: Intended Audience :: Science/Research
Classifier: Intended Audience :: Developers
Classifier: License :: OSI Approved :: GNU General Public License v3 (GPLv3)
Classifier: Programming Language :: C
Classifier: Programming Language :: C++
Classifier: Programming Language :: Python
Classifier: Topic :: Software Development
Classifier: Topic :: Scientific/Engineering
Classifier: Operating System :: Microsoft :: Windows
Classifier: Operating System :: POSIX
Classifier: Operating System :: Unix
Classifier: Operating System :: MacOS
Classifier: Programming Language :: Python :: 3
Classifier: Programming Language :: Python :: 3.9
Classifier: Programming Language :: Python :: 3.10
Classifier: Programming Language :: Python :: 3.11
Classifier: Programming Language :: Python :: 3.12
Classifier: Programming Language :: Python :: 3.13
Classifier: Programming Language :: Python :: Implementation :: CPython
Requires-Python: >=3.9
License-File: LICENSE
Requires-Dist: matplotlib>=3.6.2
Requires-Dist: numpy>=2.0
Requires-Dist: scikit-learn>=1.2.2
Requires-Dist: scipy>=1.12.0
Provides-Extra: dev
Requires-Dist: pre-commit>=3.8.0; extra == "dev"
Requires-Dist: pytest>=8.3.3; extra == "dev"
Requires-Dist: pytest-cov>=5.0.0; extra == "dev"
Requires-Dist: pandas; extra == "dev"
Requires-Dist: cython>=3.0; extra == "dev"
Requires-Dist: setuptools>=61.0; extra == "dev"
Requires-Dist: black>=24.3.0; extra == "dev"
Requires-Dist: ruff>=0.4.8; extra == "dev"
Provides-Extra: doc
Requires-Dist: pandas; extra == "doc"
Requires-Dist: networkx>=3.3; extra == "doc"
Requires-Dist: sphinx>=8.1.3; extra == "doc"
Requires-Dist: sphinx_gallery>=0.18.0; extra == "doc"
Requires-Dist: sphinx-copybutton>=0.5.2; extra == "doc"
Requires-Dist: pydata-sphinx-theme>=0.15.3; extra == "doc"
Requires-Dist: sphinxcontrib-email>=0.3.6; extra == "doc"
Requires-Dist: sphinx-remove-toctrees>=1.0.0; extra == "doc"
Requires-Dist: sphinx-prompt>=1.9.0; extra == "doc"
Requires-Dist: sphinx_design>=0.6.1; extra == "doc"
Requires-Dist: sphinxcontrib.sass>=0.3.4; extra == "doc"
Dynamic: license-file
